{
  "level": 1880,
  "hard": true,
  "rows": 16,
  "cols": 16,
  "palette": {
    "B": "#1e90ff",
    "C": "#00d2d3",
    "G": "#2ed573",
    "O": "#ff9f43",
    "R": "#ff4757",
    "Y": "#ffd700"
  },
  "grid": [
    ".....Y....Y.....",
    ".....OR..RO.....",
    ".....RB..BR.....",
    ".YY..BCCCCB..YY.",
    "..ORB.CGGC.BRO..",
    "...BCCGYYGCCB...",
    "....CGYOOYGC....",
    "RBCCGYORROYGCCBR",
    "RBCCGYORROYGCCBR",
    "....CGYOOYGC....",
    "...BCCGYYGCCB...",
    "..ORB.CGGC.BRO..",
    ".YY..BCCCCB..YY.",
    ".....RB..BR.....",
    ".....OR..RO.....",
    ".....Y....Y....."
  ],
  "story": "💥 보스! 크리스탈 만다라",
  "dialogue": {
    "intro": [
      {
        "name": "유리",
        "color": "#ff8fc7",
        "face": "🤩",
        "who": "H",
        "text": "색이 정말 다양하다!"
      }
    ],
    "outro": [
      {
        "name": "준",
        "color": "#5aa9ff",
        "face": "😄",
        "who": "M",
        "text": "하나씩 맞춰보자."
      }
    ]
  }
}