{
  "level": 1605,
  "hard": true,
  "rows": 16,
  "cols": 16,
  "palette": {
    "B": "#1e90ff",
    "C": "#00d2d3",
    "G": "#2ed573",
    "O": "#ff9f43",
    "P": "#c44dff",
    "Y": "#ffd700"
  },
  "grid": [
    "................",
    "...OPP....PPO...",
    "...PPBB..BBPP...",
    "....BCC..CCB....",
    "....CCGGGGCC....",
    ".....GGYYGG.....",
    "..BCGGYYYYGGCB..",
    "PPBCGYYOOYYGCBPP",
    "PPBCGYYOOYYGCBPP",
    "..BCGGYYYYGGCB..",
    ".....GGYYGG.....",
    "....CCGGGGCC....",
    "....BCC..CCB....",
    "...PPBB..BBPP...",
    "...OPP....PPO...",
    "................"
  ],
  "story": "💥 보스! 젬 보스",
  "dialogue": null
}