{
  "level": 751,
  "hard": false,
  "rows": 13,
  "cols": 13,
  "palette": {
    "G": "#2ed573",
    "N": "#ff8fc7",
    "O": "#ff9f43",
    "R": "#ff4757",
    "Y": "#ffd700"
  },
  "grid": [
    ".............",
    "......RR.....",
    "...NNNRRRR...",
    "..NNNNRRRRR..",
    "..NNNNRRRRR..",
    "..NNNNRRRRR..",
    "..GGGGOOOOOO.",
    "..YYYYYOOOO..",
    "..YYYYYOOOO..",
    "..YYYYYOOOO..",
    "...YYYYOOO...",
    "......YO.....",
    "............."
  ],
  "story": "🔷 보석",
  "dialogue": null
}